MANIFEST.in
README.md
setup.py
bin/my_names.bat
my_names_P_T.egg-info/PKG-INFO
my_names_P_T.egg-info/SOURCES.txt
my_names_P_T.egg-info/dependency_links.txt
my_names_P_T.egg-info/requires.txt
my_names_P_T.egg-info/top_level.txt
my_names_pac/__init__.py
my_names_pac/my_names.py