Metadata-Version: 2.1
Name: my-names-P-T
Version: 1.0.0
Summary: Generate random names with lenght
Home-page: UNKNOWN
Author: Przemek Tworkowski
Author-email: po-tworek@o2.pl
License: UNKNOWN
Keywords: random names
Platform: UNKNOWN
